tender/__init__.py
tender/__main__.py
tender-0.1.dist-info/LICENSE
tender-0.1.dist-info/METADATA
tender-0.1.dist-info/WHEEL
tender-0.1.dist-info/entry_points.txt
tender-0.1.dist-info/top_level.txt
tender-0.1.dist-info/RECORD
