Metadata-Version: 2.1
Name: tender
Version: 0.1
Summary: tender
Home-page: https://github.com/pycontribs/tender
Author: Sorin Sbarnea
Author-email: sorin.sbarnea@gmail.com
Maintainer: Sorin Sbarnea
Maintainer-email: sorin.sbarnea@gmail.com
License: MIT
Project-URL: Source, https://github.com/pycontribs/tender
Project-URL: Tracker, https://github.com/pycontribs/tender
Keywords: github
Platform: any
Classifier: Development Status :: 5 - Production/Stable
Classifier: Intended Audience :: Developers
Classifier: License :: OSI Approved :: MIT License
Classifier: Operating System :: POSIX
Classifier: Operating System :: Microsoft :: Windows
Classifier: Operating System :: MacOS :: MacOS X
Classifier: Topic :: Software Development :: Testing
Classifier: Topic :: Software Development :: Libraries
Classifier: Topic :: Utilities
Classifier: Programming Language :: Python :: 3
Classifier: Programming Language :: Python :: 3.6
Classifier: Programming Language :: Python :: 3.7
Classifier: Programming Language :: Python :: 3.8
Requires-Python: >=3.6
Requires-Dist: blessings
Requires-Dist: click
Requires-Dist: click-help-colors (>=0.8)
Requires-Dist: pygments
Requires-Dist: pyyaml
Requires-Dist: requests
Requires-Dist: github3.py
Requires-Dist: gitpython
Requires-Dist: git-url-parse
